yastr/__init__.py
yastr/config.py
yastr/fixtures.py
yastr/plugin.py
yastr/utils.py
yastr-0.1.0.dist-info/entry_points.txt
yastr-0.1.0.dist-info/LICENSE
yastr-0.1.0.dist-info/WHEEL
yastr-0.1.0.dist-info/METADATA
yastr-0.1.0.dist-info/RECORD
