Metadata-Version: 2.1
Name: yastr
Version: 0.1.0
Summary: Yet another simple test runner
Home-page: https://github.com/codetent/yastr
License: MIT
Keywords: test,testing,runner,pytest,executable
Author: Christoph Swoboda
Author-email: codetent@gmail.com
Requires-Python: >=3.8,<3.11
Classifier: Development Status :: 3 - Alpha
Classifier: Environment :: Console
Classifier: Framework :: Pytest
Classifier: Intended Audience :: Developers
Classifier: License :: OSI Approved :: MIT License
Classifier: Operating System :: MacOS
Classifier: Operating System :: Microsoft :: Windows
Classifier: Operating System :: POSIX :: Linux
Classifier: Programming Language :: Python :: 3
Classifier: Programming Language :: Python :: 3.10
Classifier: Programming Language :: Python :: 3.8
Classifier: Programming Language :: Python :: 3.9
Classifier: Topic :: Software Development :: Testing
Requires-Dist: anyconfig[template,yaml] (>=0.13.0,<0.14.0)
Requires-Dist: marshmallow-dataclass[union] (>=8.5.3,<9.0.0)
Requires-Dist: pytest (>=7.1.1,<8.0.0)
Requires-Dist: wrapt (>=1.14.0,<2.0.0)
Project-URL: Repository, https://github.com/codetent/yastr
